bupt_external_web/__init__.py
bupt_internal/BUPT_Tool.py
bupt_internal/__init__.py
bupt_tools-0.2.3.dist-info/METADATA
bupt_tools-0.2.3.dist-info/WHEEL
bupt_tools-0.2.3.dist-info/entry_points.txt
bupt_tools-0.2.3.dist-info/RECORD
