Metadata-Version: 2.1
Name: BUPT-Tools
Version: 0.2.3
Summary: A series of tools that can be used in your BUPT college life.
Author-Email: EliorFoy <1700118540@qq.com>
License: MIT
Requires-Python: >=3.10
Requires-Dist: requests>=2.32.3
Requires-Dist: loguru>=0.7.2
Requires-Dist: beautifulsoup4>=4.12.3
Requires-Dist: deprecation>=2.1.0
